jinja2_pimport/__init__.py
jinja2_pimport/pimportextension.py
jinja2_pimport-0.1.6.dist-info/DESCRIPTION.rst
jinja2_pimport-0.1.6.dist-info/METADATA
jinja2_pimport-0.1.6.dist-info/RECORD
jinja2_pimport-0.1.6.dist-info/WHEEL
jinja2_pimport-0.1.6.dist-info/metadata.json
jinja2_pimport-0.1.6.dist-info/top_level.txt
